BinanceAsyncWebsocket/BinanceAsyncWebsocket.py
BinanceAsyncWebsocket/BinanceAsyncWebsocket2.py
BinanceAsyncWebsocket/BinanceFapiAsyncWs.py
BinanceAsyncWebsocket/__init__.py
BinanceAsyncWebsocket-3.0.3.dist-info/LICENSE
BinanceAsyncWebsocket-3.0.3.dist-info/METADATA
BinanceAsyncWebsocket-3.0.3.dist-info/WHEEL
BinanceAsyncWebsocket-3.0.3.dist-info/top_level.txt
BinanceAsyncWebsocket-3.0.3.dist-info/RECORD
